LICENSE
README.md
pyproject.toml
moirae/__init__.py
moirae/cache.py
moirae/data.py
moirae/executor.py
moirae/graph.py
moirae/hash.py
moirae/latch.py
moirae/node.py
moirae/serialize.py
moirae.egg-info/PKG-INFO
moirae.egg-info/SOURCES.txt
moirae.egg-info/dependency_links.txt
moirae.egg-info/requires.txt
moirae.egg-info/top_level.txt