Metadata-Version: 2.1
Name: moirae
Version: 0.3.1
Summary: A workflow execution engine supports static DAGs.
Author-email: Zhongqi Luo <luozhongqi@mail.com>
Maintainer-email: Zhongqi Luo <luozhongqi@mail.com>
License: MIT License
Requires-Python: >=3.8
License-File: LICENSE
Requires-Dist: networkx>=3.0
Requires-Dist: pydantic>=2.6
Requires-Dist: msgpack>=1.0
Requires-Dist: lz4>=4.2
